minetest_python_nsi/__init__.py
minetest_python_nsi/blocs.py
minetest_python_nsi/connection.py
minetest_python_nsi/main.py
minetest_python_nsi/minetest_python_nsi.py
minetest_python_nsi/util.py
minetest_python_nsi-0.3.0.dist-info/METADATA
minetest_python_nsi-0.3.0.dist-info/WHEEL
minetest_python_nsi-0.3.0.dist-info/top_level.txt
minetest_python_nsi-0.3.0.dist-info/RECORD
