Metadata-Version: 2.1
Name: minetest-python-nsi
Version: 0.3.0
Summary: Exécuter des scripts Python dans Minetest
Author: Christophe Viroulaud
Author-email: christophe.viroulaud@ac-bordeaux.fr
License: GPL V3
Keywords: minetest NSI Python
Platform: ALL
Classifier: Topic :: Education
Classifier: Topic :: Games/Entertainment
Classifier: Programming Language :: Python
